flatiron_cleaner/__init__.py
flatiron_cleaner/breast.py
flatiron_cleaner/colorectal.py
flatiron_cleaner/general.py
flatiron_cleaner/headneck.py
flatiron_cleaner/main.py
flatiron_cleaner/melanoma.py
flatiron_cleaner/merge_utils.py
flatiron_cleaner/nsclc.py
flatiron_cleaner/prostate.py
flatiron_cleaner/renal.py
flatiron_cleaner/test.py
flatiron_cleaner/urothelial.py
flatiron_cleaner-0.1.12.dist-info/licenses/LICENSE
flatiron_cleaner-0.1.12.dist-info/METADATA
flatiron_cleaner-0.1.12.dist-info/WHEEL
flatiron_cleaner-0.1.12.dist-info/top_level.txt
flatiron_cleaner-0.1.12.dist-info/RECORD
