Metadata-Version: 2.4
Name: flatiron_cleaner
Version: 0.1.12
Summary: A Python package for cleaning and harmonizing Flatiron Health cancer data
Author-email: Xavier Orcutt <xavierorcutt@gmail.com>
License: MIT
Project-URL: Homepage, https://github.com/xavier-orcutt/FlatironCleaner
Project-URL: Bug Tracker, https://github.com/xavier-orcutt/FlatironCleaner/issues
Project-URL: Documentation, https://github.com/xavier-orcutt/FlatironCleaner#readme
Keywords: cancer,healthcare,data,flatiron
Classifier: Programming Language :: Python :: 3.10
Classifier: Programming Language :: Python :: 3.11
Classifier: Programming Language :: Python :: 3.12
Classifier: Programming Language :: Python :: 3.13
Classifier: License :: OSI Approved :: MIT License
Classifier: Operating System :: OS Independent
Classifier: Intended Audience :: Science/Research
Classifier: Intended Audience :: Healthcare Industry
Classifier: Topic :: Scientific/Engineering :: Bio-Informatics
Classifier: Topic :: Scientific/Engineering :: Medical Science Apps.
Requires-Python: >=3.10
License-File: LICENSE
Requires-Dist: numpy>=2.2.0
Requires-Dist: pandas>=2.2.0
Requires-Dist: python-dateutil>=2.9.0
Requires-Dist: pytz>=2024.2
Requires-Dist: tzdata>=2025.1
Dynamic: license-file
